larcv/__init__.py
larcv/batch_pydata.py
larcv/data_generator.py
larcv/distributed_queue_interface.py
larcv/larcv_io_enums.py
larcv/larcv_writer.py
larcv/pylarcv.cpython-36m-darwin.so
larcv/queueloader.py
larcv/include/app/queueio/BatchData.h
larcv/include/app/queueio/BatchDataQueue.h
larcv/include/app/queueio/BatchDataQueueFactory.h
larcv/include/app/queueio/BatchFillerPIDLabel.h
larcv/include/app/queueio/BatchFillerSparseTensor.h
larcv/include/app/queueio/BatchFillerTemplate.h
larcv/include/app/queueio/BatchFillerTensor.h
larcv/include/app/queueio/BatchHolder.h
larcv/include/app/queueio/QueueIOTypes.h
larcv/include/app/queueio/QueueProcessor.h
larcv/include/app/queueio/queueio.h
larcv/include/larcv3/app/filter/EmptyImageFilter.h
larcv/include/larcv3/app/filter/EmptyTensorFilter.h
larcv/include/larcv3/app/filter/MCSingleParticleFilter.h
larcv/include/larcv3/app/filter/ParticleCountFilter.h
larcv/include/larcv3/app/filter/QSumFilter.h
larcv/include/larcv3/app/imagemod/Downsample.h
larcv/include/larcv3/app/imagemod/Image2DFromTensor2D.h
larcv/include/larcv3/app/imagemod/Tensor2DFromImage2D.h
larcv/include/larcv3/app/imagemod/TensorFromCluster.h
larcv/include/larcv3/app/imagemod/Threshold.h
larcv/include/larcv3/app/sbnd_imagemod/CompressAndEmbed.h
larcv/include/larcv3/app/sbnd_imagemod/CosmicNeutrinoSegLabel.h
larcv/include/larcv3/app/sbnd_imagemod/EventPIDLabel.h
larcv/include/larcv3/app/sbnd_imagemod/ParentParticleSeg.h
larcv/include/larcv3/app/sbnd_imagemod/ParticleBoundaries.h
larcv/include/larcv3/core/base/ConfigManager.h
larcv/include/larcv3/core/base/LArCVBaseUtilFunc.h
larcv/include/larcv3/core/base/LArCVTypes.h
larcv/include/larcv3/core/base/PSet.h
larcv/include/larcv3/core/base/Parser.h
larcv/include/larcv3/core/base/Watch.h
larcv/include/larcv3/core/base/base.h
larcv/include/larcv3/core/base/larbys.h
larcv/include/larcv3/core/base/larcv_base.h
larcv/include/larcv3/core/base/larcv_logger.h
larcv/include/larcv3/core/base/stack_trace.h
larcv-3.3.4.dist-info/LICENSE
larcv-3.3.4.dist-info/METADATA
larcv-3.3.4.dist-info/WHEEL
larcv-3.3.4.dist-info/top_level.txt
larcv-3.3.4.dist-info/RECORD
