Metadata-Version: 2.1
Name: larcv
Version: 3.3.4
Summary: C++ IO and Preprocessing package for sparse neutrino data, with H5 for IO and python bindings.
Home-page: https://github.com/DeepLearnPhysics/larcv3
Author: ['Corey Adams', 'Kazuhiro Terao', 'Taritree Wongjirad', 'Marco del Tutto']
Author-email: corey.adams@anl.gov
License: MIT
Project-URL: Source Code, https://github.com/DeepLearnPhysics/larcv3
Keywords: larcv larcv3 neutrinos hdf5 h5 deep learning IO sparse
Platform: UNKNOWN
Requires-Dist: numpy
Requires-Dist: scikit-build
